pyssl/__init__.py
pyssl/cmdIf/Qt5Core.dll
pyssl/cmdIf/Qt5Network.dll
pyssl/cmdIf/__init__.py
pyssl/cmdIf/boost_python37-vc140-mt-x64-1_67.dll
pyssl/cmdIf/cmdIf.pyd
pyssl/visionIf/Qt5Core.dll
pyssl/visionIf/Qt5Network.dll
pyssl/visionIf/__init__.py
pyssl/visionIf/boost_python37-vc140-mt-x64-1_67.dll
pyssl/visionIf/visionIf.pyd
PySSL-0.0.7.dist-info/METADATA
PySSL-0.0.7.dist-info/WHEEL
PySSL-0.0.7.dist-info/top_level.txt
PySSL-0.0.7.dist-info/RECORD
