Metadata-Version: 2.1
Name: PySSL
Version: 0.0.7
Summary: Basic libraries for SSL
Home-page: UNKNOWN
Author: UNKNOWN
Author-email: UNKNOWN
License: UNKNOWN
Platform: UNKNOWN
